fuel_efficiency/__init__.py
fuel_efficiency/algorithms/__init__.py
fuel_efficiency/algorithms/a_star.py
fuel_efficiency/algorithms/context.py
fuel_efficiency/algorithms/dijkstra.py
fuel_efficiency/algorithms/path_finding.py
fuel_efficiency/entities/__init__.py
fuel_efficiency/entities/down_hill.py
fuel_efficiency/entities/node.py
fuel_efficiency/entities/plateau.py
fuel_efficiency/entities/position.py
fuel_efficiency/entities/up_hill.py
fuel_efficiency/entities/valley.py
fuel_efficiency-0.1.5.dist-info/METADATA
fuel_efficiency-0.1.5.dist-info/WHEEL
fuel_efficiency-0.1.5.dist-info/RECORD
