Metadata-Version: 2.1
Name: fuel-efficiency
Version: 0.1.5
Summary: Fuel efficiency challenge test
License: Proprietary
Author: Guilherme Lima
Author-email: guimarotto@gmail.com
Requires-Python: >=3.12,<4.0
Classifier: Development Status :: 5 - Production/Stable
Classifier: Environment :: Console
Classifier: License :: Other/Proprietary License
Classifier: Natural Language :: Portuguese (Brazilian)
Classifier: Programming Language :: Python :: 3
Classifier: Programming Language :: Python :: 3.12
Classifier: Programming Language :: Python :: 3.11
Classifier: Topic :: Software Development
Project-URL: Bug Tracker, https://github.com/gllima/fuel-efficiency/issues
Project-URL: Código, https://github.com/gllima/fuel-efficiency
